LICENSE
MANIFEST.in
README.md
setup.py
plupload/__init__.py
plupload/plupload.py
plupload.egg-info/PKG-INFO
plupload.egg-info/SOURCES.txt
plupload.egg-info/dependency_links.txt
plupload.egg-info/top_level.txt